PyLogDc/__init__.py
PyLogDc/logthis.py
pylogdc-0.1.3.dist-info/LICENSE
pylogdc-0.1.3.dist-info/METADATA
pylogdc-0.1.3.dist-info/WHEEL
pylogdc-0.1.3.dist-info/top_level.txt
pylogdc-0.1.3.dist-info/RECORD
