Metadata-Version: 2.1
Name: pylogdc
Version: 0.1.3
Summary: Python package for logging actions to Discord servers using webhooks.
Home-page: https://github.com/Trnass/PyLogDc
Author: Trnass
Author-email: admin@trnass.cz
Classifier: Programming Language :: Python :: 3
Classifier: License :: OSI Approved :: MIT License
Classifier: Operating System :: OS Independent
Requires-Python: >=3.6
License-File: LICENSE
Requires-Dist: requests
